sysprober/__init__.py
sysprober/_base/__init__.py
sysprober/_base/parse.py
sysprober/_base/readonlydict.py
sysprober/cpu/__init__.py
sysprober/cpu/cpu.py
sysprober/memory/__init__.py
sysprober/memory/memory.py
sysprober/network/__init__.py
sysprober/network/network.py
sysprober/pci/__init__.py
sysprober-0.1.2.dist-info/LICENSE
sysprober-0.1.2.dist-info/METADATA
sysprober-0.1.2.dist-info/WHEEL
sysprober-0.1.2.dist-info/top_level.txt
sysprober-0.1.2.dist-info/RECORD
