Metadata-Version: 2.1
Name: sysprober
Version: 0.1.2
Summary: Probe your Linux host for information about itself
Home-page: UNKNOWN
Author: Jason C. Nucciarone
Author-email: jason.nucciarone@canonical.com
License: Apache-2.0
Keywords: system-administration,automation
Platform: UNKNOWN
Classifier: Development Status :: 1 - Planning
Classifier: Intended Audience :: Developers
Classifier: License :: OSI Approved :: Apache Software License
Classifier: Operating System :: POSIX :: Linux
Classifier: Programming Language :: Python :: 3.8
Classifier: Programming Language :: Python :: 3.9
Classifier: Programming Language :: Python :: 3.10
Requires-Python: >=3.8
License-File: LICENSE
Requires-Dist: pydantic
